odmrawpy.libs/libgomp-d22c30c5.so.1.0.0
odmrawpy.libs/libjasper-28e96e29.so.4.0.0
odmrawpy.libs/libjpeg-bb5d9b88.so.9.4.0
odmrawpy.libs/liblcms2-cee87515.so.2.0.10
odmrawpy.libs/libraw_r-2b223eab.so.23.0.0
rawpy/__init__.py
rawpy/_rawpy.cpython-38-aarch64-linux-gnu.so
rawpy/_version.py
rawpy/enhance.py
odmrawpy-0.24.1.dist-info/LICENSE
odmrawpy-0.24.1.dist-info/LICENSE.LibRaw
odmrawpy-0.24.1.dist-info/METADATA
odmrawpy-0.24.1.dist-info/WHEEL
odmrawpy-0.24.1.dist-info/top_level.txt
odmrawpy-0.24.1.dist-info/RECORD
